{"bio":{"tier":5,"orientation":"right","name":"Skald of War","family":"Aloysia's Chosen","summonOnly":false,"leader":false,"cost":"180","maxStacks":2,"sprite":{"x":832,"y":160,"spritesheet":"DungeonCrawl_ProjectUtumnoTileset.png","w":32,"h":32}},"ai":{"behavior":"when use Move to most ally\n!when self has effect -Bulwark of Winter- use -Bulwark of Winter- select:self\n!when self has effect -Dream of War- use -Dream of War- select:self\nwhen 3 ability enemy use -Blizzard-\nwhen use Move for ability -Blizzard- on enemy\nwhen use -Hail- on strongest enemy\nwhen use Defend"},"abilities":{"abilities":["Blizzard","Hail","Energy Field","Bulwark of Winter","Dream of War"]},"sounds":{"turnStart":""},"stats":{"health":55,"mana":20,"attack":16,"defence":12,"spellPower":8,"spellResistance":40,"damage":1,"apr":2,"tpr":2,"movement":5,"initiative":13,"range":7}}