{"bio":{"name":"Clear Fountain","sprite":[{"x":672,"y":352,"spritesheet":"DungeonCrawl_ProjectUtumnoTileset.png","w":32,"h":32},{"x":704,"y":352,"spritesheet":"DungeonCrawl_ProjectUtumnoTileset.png","w":32,"h":32}]},"stats":{"walkable":false,"cover":false,"animation":true,"composite":false,"ingredient":false},"adventure":{"event":"click","action":"give item","item":"d144a149-30cb-1c4b-702b-2ec47d3199ca","actionAmount":2,"charges":1,"chargeActivation":"per adventure","consumable":false,"description":"This well of seemingly ordinary water is cool to the touch and clear as if distilled. As you look at it you become calm and all fear dissipates. Shortly, you experience being back in your mother's womb."},"inventory":{"consumable":false,"event":"","target":"","action":"","ability":""}}