{"bio":{"tier":3,"name":"Chain Lightning","type":"active","activation":"when selected","condition":"","description":"Cast a powerful lightning Spell that chains from one enemy to the next. It chains to up to 4 additional enemeies after the first. Chain Lightning cannot hit the same enemy more than once.","sprite":{"x":512,"y":1344,"spritesheet":"DungeonCrawl_ProjectUtumnoTileset.png","w":32,"h":32}},"animation":{"template":""},"stats":{"shape":"point","radius":1,"target":"actor","targetFamily":"enemies","range":4,"duration":0,"resourceCost":3,"resourceType":"mana","element":"air","effect":"","multiplier":100,"minPower":1,"maxPower":10,"stacks":1,"source":"spell","attribute":"","summon":"","ailment":"","vigor":"","special":"chain","selections":1}}